dh5/__config__.py
dh5/__init__.py
dh5/errors.py
dh5/types.py
dh5/dh5_class/__init__.py
dh5/dh5_class/data_transformation.py
dh5/dh5_class/dict_structure.py
dh5/dh5_class/h5py_utils.py
dh5/dh5_class/internal_classes.py
dh5/dh5_class/main.py
dh5/dh5_class/transformation_types/__init__.py
dh5/dh5_class/transformation_types/function_save.py
dh5/dh5_types/__init__.py
dh5/dh5_types/h5_np_array.py
dh5/jsn/__init__.py
dh5/jsn/decoders.py
dh5/jsn/encoders.py
dh5/jsn/methods.py
dh5/path/__init__.py
dh5/path/path_class.py
dh5/utils/__init__.py
dh5/utils/async_utils.py
dh5/utils/random_utils.py
dh5-0.8.1.dist-info/LICENSE
dh5-0.8.1.dist-info/METADATA
dh5-0.8.1.dist-info/WHEEL
dh5-0.8.1.dist-info/top_level.txt
dh5-0.8.1.dist-info/RECORD
