Metadata-Version: 2.1
Name: dh5
Version: 0.8.1
Summary: Data H5. Work with hdf5 as classical dictionary.
Home-page: https://github.com/kyrylo-gr/dh5
Author: kyrylo.gr | LKB-OMQ
Author-email: git@kyrylo.gr
Classifier: Programming Language :: Python :: 3
Classifier: Operating System :: OS Independent
Requires-Python: >=3.8
License-File: LICENSE
Requires-Dist: numpy
Requires-Dist: h5py
Provides-Extra: all
Provides-Extra: dev
Requires-Dist: matplotlib ; extra == 'dev'
Requires-Dist: pytest ; extra == 'dev'
Requires-Dist: check-manifest ; extra == 'dev'
